cifar_utils/__init__.py
cifar_utils/setup.py
cifar_utils-0.2.dist-info/METADATA
cifar_utils-0.2.dist-info/WHEEL
cifar_utils-0.2.dist-info/top_level.txt
cifar_utils-0.2.dist-info/RECORD
