Metadata-Version: 2.1
Name: cifar-utils
Version: 0.2
Author: Jyothsna Lakshminarayanan
Classifier: Programming Language :: Python :: 3
Classifier: License :: OSI Approved :: MIT License
Classifier: Operating System :: OS Independent
Requires-Python: >=3.6
